<?xml version = '1.0' encoding = 'UTF-8'?>
<Relation class="oracle.dbtools.crest.model.design.logical.Relation" name="TestSuiteSource" id="CCD38E11-8557-EB34-2651-07EB29E83FA6" directorySegmentName="seg_0">
<createdBy>bird</createdBy>
<createdTime>2012-08-21 08:56:11 UTC</createdTime>
<ownerDesignName>TestManagerDatabase</ownerDesignName>
<engineerTo>
<item key="B082B14A-BEA8-D8A7-D661-197F34766ED3" value="true"/>
</engineerTo>
<identifying>false</identifying>
<optionalSource>true</optionalSource>
<optionalTarget>true</optionalTarget>
<sourceCardinality>1</sourceCardinality>
<sourceEntity>24150FB1-B00F-4F69-6F77-49ECB58F0F66</sourceEntity>
<targetCardinalityString>*</targetCardinalityString>
<targetEntity>6A886CEE-579B-48FF-63F6-0FB03393FBF6</targetEntity>
<transferable>true</transferable>
</Relation>